{
  "format_version": "1.8.0",
  "minecraft:entity": {
    "description": {
      "identifier": "badger:chunk_drag_wall",
      "runtime_identifier": "badger:buildable",
      "is_summonable": true
    },
    "components": {
      "badger:buildable_requirement": {
        "unlock": [
          {
            "item": "custom_tech_tree_wall",
            "amount": 1
          }
        ]
      },
      "badger:template": {
        "parent": "badger:chunk_drag_wall",
        "game_mode": "lcu_pvp"
      }
    }
  }
}