{
  "format_version": "1.8.0",
  "minecraft:entity": {
    "description": {
      "identifier": "badger:unlock_poi_golem",
      "runtime_identifier": "badger:buildable",
      "is_summonable": true
    },
    "components": {
      "badger:buildable_presentation": {
        "icon": "structure_unlock_poi_golem",
        "tooltip_title": "structures.unlock.poi.golem.name",
        "tactical_description": "structures.unlock.poi.golem.tactical_description",
        "tooltip_description": "structures.unlock.poi.golem.description",
        "buildable_category": "village",
        "sort_order": 200
      },
      "badger:buildable_requirement": {
        "recipe": [
          {
            "item": "stone",
            "amount": 100
          },
          {
            "item": "xp_common",
            "amount": 100
          }
        ],
        "unlock": [
          {
            "item": "unlock_poi_golem_upgrade",
            "amount": 1
          }
        ],
        "ticket_cost": [
          {
            "ticket": "build",
            "amount": 1
          }
        ],
        "invalid_block_tags": [
          "water",
          "lava",
          
          
          "barrier",
          "world_hazard"
        ]
      },
      "badger:rewards": {
        "reward": [
          {
            "item": "unlock_poi_golem_resource",
            "amount": 1
          },
          {
            "item": "ui_tracking_poi_golem",
            "amount": 1
          }
        ]
      },
      "badger:buildable_structure": {
        "nbt_file": "wof_upgrade_small",
        "build_time": 10,
        "construction_start_trigger": "on_construction_start",
        "construction_end_trigger": "on_construction_end",
        "buildable_placed_player_trigger": "on_building_unlock_poi_golem"
      },
      "badger:nbt_parts": {
        "locator": "badger:locator_swappable_icon",
        "block": "block_deco_xp_ally"
      },
      "badger:buildable_destruction": {
        "particle_effect": "badger:fx_destruction_stone_small"
      },
      "badger:action_tickets": {
        "action_tickets": {
          "cc": 0,
          "rc": 0
        }
      },
      "badger:tags": {
        "tags": [
          "buildable",
          "buildable_combat",
          "buildable_structure",
          "donotattack",
          "unlock_poi_golem",
          "player_upgrade"
        ]
      },
      "badger:interactable": {
        "interactions": [
          {
            "name": "interaction_zone",
            "range": 7,
            "include_tags": [
              "player"
            ],
            "exclude_tags": [],
            "alliance_rule_filter": "friendly",
            "input_layout_override": "overlay_gameplay_interaction"
          }
        ]
      },
      "badger:template": [
        "badger:template_upgrade_xp",
        "badger:template_structure_player"
      ]
    }
  }
}