{
    "format_version": "1.8.0",
    "minecraft:entity": {
        "description": {
            "identifier": "badger:wmap_audio_invasion_mob_alliance_silverfish_post_alliance",
            "runtime_identifier": "badger:badger_mob",
            "is_summonable": false
        },
        "components": {
            "badger:map3_tooltip_audio": {
                "event_id": "map_silverfishes_post_alliance",
                "event_type": "PresentationAction",
                "selection_time": 2.0,
                "cooldown_time": 20.0
            }
        }
    }
}
