{
  "format_version": "1.8.0",
  "animations": {
    "animation.endermite_corrupted.move_a": {
      "anim_time_update": "(query.anim_time + (query.delta_time * 1))",
      "blend_weight": "1",
      "loop": true,
      "override_previous_animation": true,
      "bones": {
        "section_0": {
          "lod_distance": 0,
          "rotation": {
            "0.0": [
              0,
              0,
              0
            ],
            "0.25": [
              2.5,
              0,
              0
            ],
            "0.5": [
              -2.5,
              0,
              0
            ],
            "0.75": [
              2.5,
              0,
              0
            ],
            "1.0": [
              0,
              0,
              0
            ],
            "lod_distance": 0
          },
          "position": {
            "0.0": [
              0,
              0,
              0
            ],
            "0.25": [
              0.0625,
              0,
              0
            ],
            "0.5": [
              0,
              0,
              0
            ],
            "0.75": [
              -0.0625,
              0,
              0
            ],
            "1.0": [
              0,
              0,
              0
            ],
            "lod_distance": 0
          }
        },
        "section_1": {
          "lod_distance": 0,
          "rotation": {
            "0.0": [
              0,
              0,
              0
            ],
            "0.25": [
              0,
              0,
              5
            ],
            "0.5": [
              0,
              0,
              0
            ],
            "0.75": [
              0,
              0,
              -5
            ],
            "1.0": [
              0,
              0,
              0
            ],
            "lod_distance": 0
          }
        },
        "section_2": {
          "lod_distance": 0,
          "position": {
            "0.0": [
              0,
              0,
              0
            ],
            "0.25": [
              -0.125,
              0,
              0
            ],
            "0.5": [
              0,
              0,
              0
            ],
            "0.75": [
              0.1875,
              0,
              0
            ],
            "1.0": [
              0,
              0,
              0
            ],
            "lod_distance": 0
          }
        },
        "section_3": {
          "lod_distance": 0,
          "rotation": {
            "0.0": [
              0,
              0,
              0
            ],
            "0.25": [
              -5,
              0,
              -5
            ],
            "0.5": [
              0,
              0,
              0
            ],
            "0.75": [
              -5,
              0,
              5
            ],
            "1.0": [
              0,
              0,
              0
            ],
            "lod_distance": 0
          },
          "position": {
            "0.0": [
              0,
              0,
              0
            ],
            "0.25": [
              -0.0625,
              0,
              0
            ],
            "0.5": [
              0,
              0,
              0
            ],
            "0.75": [
              0.0625,
              0,
              0
            ],
            "1.0": [
              0,
              0,
              0
            ],
            "lod_distance": 0
          }
        }
      }
    },
    "animation.endermite_corrupted.attack_a": {
      "anim_time_update": "(query.anim_time + (query.delta_time * 1))",
      "blend_weight": "1",
      "override_previous_animation": true,
      "bones": {
        "section_1": {
          "lod_distance": 0,
          "rotation": {
            "0.0": [
              0,
              0,
              0
            ],
            "0.5": [
              5,
              0,
              0
            ],
            "0.6667": [
              10,
              0,
              0
            ],
            "1.0": [
              0,
              0,
              0
            ],
            "lod_distance": 0
          },
          "position": {
            "0.0": [
              0,
              0,
              0
            ],
            "0.0833": [
              0,
              0,
              0
            ],
            "lod_distance": 0
          },
          "scale": {
            "0.0": [
              1,
              1,
              1
            ],
            "0.0833": [
              1,
              1,
              1
            ],
            "lod_distance": 0
          }
        },
        "section_2": {
          "lod_distance": 0,
          "rotation": {
            "0.0": [
              0,
              0,
              0
            ],
            "0.6667": [
              12.5,
              0,
              0
            ],
            "1.0": [
              0,
              0,
              0
            ],
            "lod_distance": 0
          },
          "position": {
            "0.0": [
              0,
              0,
              0
            ],
            "0.6667": [
              0,
              0.0625,
              0
            ],
            "1.0": [
              0,
              0,
              0
            ],
            "lod_distance": 0
          }
        },
        "section_0": {
          "lod_distance": 0,
          "rotation": {
            "0.0": [
              0,
              0,
              0
            ],
            "0.3333": [
              0,
              10,
              0
            ],
            "0.5833": [
              12.5,
              0,
              0
            ],
            "0.75": [
              7.614352250409411,
              -9.913580674589866,
              -1.3184461832734087
            ],
            "1.0": [
              0,
              0,
              0
            ],
            "lod_distance": 0
          },
          "position": {
            "0.0": [
              0,
              0,
              0
            ],
            "0.0833": [
              0,
              0,
              0
            ],
            "lod_distance": 0
          },
          "scale": {
            "0.0": [
              1,
              1,
              1
            ],
            "0.5": [
              1,
              0.9999999999999997,
              1
            ],
            "0.6667": [
              1,
              1.4000000000000004,
              1
            ],
            "0.8333": [
              1,
              0.8777999999999999,
              1
            ],
            "1.0": [
              1,
              0.9999999999999997,
              1
            ],
            "lod_distance": 0
          }
        },
        "section_3": {
          "lod_distance": 0,
          "rotation": {
            "0.0": [
              0,
              0,
              0
            ],
            "0.25": [
              -2.4786389426803908,
              -0.3262137097226514,
              -7.492942810808472
            ],
            "0.5": [
              -5,
              0,
              0
            ],
            "0.75": [
              -2.4620664797216705,
              0.4339868564493372,
              9.990674059621597
            ],
            "1.0": [
              0,
              0,
              0
            ],
            "lod_distance": 0
          },
          "position": {
            "0.0": [
              0,
              0,
              0
            ],
            "0.0833": [
              0,
              0,
              0
            ],
            "lod_distance": 0
          },
          "scale": {
            "0.0": [
              1,
              1,
              1
            ],
            "0.0833": [
              1,
              1,
              1
            ],
            "lod_distance": 0
          }
        }
      }
    },
    "animation.endermite_corrupted.idle_a": {
      "anim_time_update": "(query.anim_time + (query.delta_time * 1))",
      "blend_weight": "1",
      "loop": true,
      "bones": {
        "section_2": {
          "lod_distance": 0,
          "rotation": {
            "0.0": [
              0,
              0,
              0
            ],
            "0.5": [
              0,
              0,
              0
            ],
            "1.0": [
              0,
              0,
              7.5
            ],
            "1.375": [
              0,
              0,
              17.5
            ],
            "1.75": [
              0,
              0,
              12.5
            ],
            "2.125": [
              0,
              0,
              17.5
            ],
            "2.4167": [
              0,
              0,
              27.5
            ],
            "2.7083": [
              0,
              0,
              -2.5
            ],
            "3.0833": [
              0,
              0,
              -19.72
            ],
            "3.3333": [
              0,
              0,
              -12.219999999999999
            ],
            "3.5": [
              0,
              0,
              -19.72
            ],
            "3.7083": [
              0,
              0,
              -9.719999999999999
            ],
            "4.125": [
              0,
              0,
              0
            ],
            "5.0": [
              0,
              0,
              0
            ],
            "lod_distance": 0
          },
          "position": {
            "0.0": [
              0,
              0,
              0
            ],
            "0.5": [
              0,
              0,
              0
            ],
            "1.0": [
              -0.0625,
              0.125,
              0
            ],
            "1.375": [
              -0.1875,
              0,
              0
            ],
            "2.125": [
              -0.1875,
              0,
              0
            ],
            "2.4167": [
              -0.1875,
              0,
              0
            ],
            "2.7083": [
              -0.0625,
              0.125,
              0
            ],
            "3.0833": [
              0.166875,
              0,
              0
            ],
            "3.3333": [
              0.166875,
              0,
              0
            ],
            "3.5": [
              0.166875,
              0,
              0
            ],
            "3.7083": [
              0.104375,
              0.125,
              0
            ],
            "4.125": [
              0,
              0,
              0
            ],
            "5.0": [
              0,
              0,
              0
            ],
            "lod_distance": 0
          }
        },
        "section_0": {
          "lod_distance": 0,
          "rotation": {
            "0.0": [
              0,
              0,
              0
            ],
            "0.3333": [
              -5,
              0,
              0
            ],
            "0.6667": [
              1.0309810540200304,
              2.499595793615299,
              0.044968339811475744
            ],
            "1.0833": [
              8.538006690692582,
              2.4723285648365163,
              0.3710484164466834
            ],
            "1.625": [
              -4.254034055345528,
              2.4931211147199974,
              -0.185388244886326
            ],
            "1.9583": [
              0,
              0,
              0
            ],
            "2.4167": [
              7.5,
              0,
              0
            ],
            "3.5": [
              0,
              0,
              0
            ],
            "3.6667": [
              -2.5,
              0,
              0
            ],
            "3.8333": [
              12.81,
              0,
              0
            ],
            "4.1667": [
              4.1342628587080075,
              -0.3613825517991245,
              4.986956247043963
            ],
            "4.4583": [
              2.6949414177751714,
              0.1177393688358461,
              -4.250199363052397
            ],
            "4.7083": [
              0,
              0,
              0
            ],
            "5.0": [
              0,
              0,
              0
            ],
            "lod_distance": 0
          }
        },
        "section_1": {
          "lod_distance": 0,
          "rotation": {
            "0.0": [
              0,
              0,
              0
            ],
            "0.4583": [
              -5,
              0,
              2.2916666666665515
            ],
            "1.0": [
              5,
              0,
              5
            ],
            "1.7917": [
              -3.9583333333334485,
              0,
              1.0416666666665515
            ],
            "2.0": [
              0,
              0,
              0
            ],
            "2.4167": [
              7.5,
              0,
              -2.380952380952185
            ],
            "2.875": [
              0,
              0,
              -5
            ],
            "3.125": [
              -5,
              0,
              -3
            ],
            "3.5": [
              0,
              0,
              0
            ],
            "3.6667": [
              7.5,
              0,
              1.111111111111186
            ],
            "4.25": [
              0,
              0,
              5
            ],
            "4.4167": [
              -2.5,
              0,
              1.39
            ],
            "4.5833": [
              0,
              0,
              -2.22
            ],
            "5.0": [
              0,
              0,
              0
            ],
            "lod_distance": 0
          }
        },
        "section_3": {
          "lod_distance": 0,
          "rotation": {
            "0.0": [
              0,
              0,
              0
            ],
            "0.25": [
              -7.5,
              0,
              5
            ],
            "0.5833": [
              6.428571428571722,
              0,
              4.047619047619082
            ],
            "1.0": [
              4.499153562562732,
              -0.5916952255470278,
              10.33389925949892
            ],
            "1.1667": [
              -1.2507467582804566,
              0.49339444573548463,
              -6.3561295332125525
            ],
            "1.5": [
              6.749551945031726,
              0.2960366674413308,
              -3.8136777199275094
            ],
            "1.7083": [
              3.8811700087766803,
              0.6847327948607199,
              -9.70738027447871
            ],
            "2.0": [
              0,
              0,
              0
            ],
            "2.2917": [
              0,
              0,
              7.5
            ],
            "2.625": [
              12.5,
              0,
              -2.0700000000000003
            ],
            "2.875": [
              0,
              0,
              -13.98
            ],
            "3.2083": [
              0,
              0,
              3.4800000000000004
            ],
            "3.5": [
              -2.5,
              0,
              0
            ],
            "3.625": [
              12.52304230222122,
              -2.1895443829489523,
              9.759731433313846
            ],
            "4.25": [
              0,
              0,
              0
            ],
            "4.4167": [
              -4.995265197606386,
              -0.21782074970724352,
              -2.4904987465251907
            ],
            "4.5833": [
              0,
              0,
              0
            ],
            "5.0": [
              0,
              0,
              0
            ],
            "lod_distance": 0
          }
        }
      }
    }
  }
}