{
  "format_version": "1.8.0", 
  "minecraft:block": {
    "description": {
      "material": "badger_metal", 
      "identifier": "badger:block_deco_piglin_banner_melee_frost"
    }, 
    "components": {
      "minecraft:block_shape": {
        "shape": "column", 
        "directional_texture": true, 
        "directional_shape": false
      }, 
      "minecraft:destroy_time": {
        "value": 10
      }, 
      "badger:block_type": {
        "tags": [
          "deco_nether", 
          "piglin_base_not_buildable"
        ]
      }, 
      "badger:terrain_type": {
        "terrain": "stone"
      }
    }
  }
}